{
    "AX": {
        "error": 0.05010589553658677, 
        "fit": "average_SEM", 
        "value": 0.16004077183703583
    }, 
    "CDD": {
        "error": 2.3472978190571605e-05, 
        "fit": "average_SEM", 
        "value": 3.518970333971083e-06
    }, 
    "H1": {
        "error": 0.040930238345790876, 
        "fit": "average_SEM", 
        "value": 0.18317976618806522
    }, 
    "H2": {
        "error": 0.11803292210413534, 
        "fit": "average_SEM", 
        "value": 0.15629626781010303
    }, 
    "L1": {
        "error": 0.263510362679404, 
        "fit": "average_SEM", 
        "value": 0.08628534059971571
    }, 
    "L2": {
        "error": 0.0513883408099078, 
        "fit": "average_SEM", 
        "value": 0.1333255154908531
    }
}